{
  "id": "b4114c28-c20a-4506-94db-91bc277339cc",
  "type": "error_solution",
  "content": {
    "error_description": "Hook系统激活但搜索没有找到相关模式",
    "solution": "这是正常现象，说明Hook系统正确响应了触发条件，但记忆系统中暂时没有匹配的模式。解决方案：1)检查搜索关键词是否准确 2)添加更多相关模式到记忆系统 3)调整搜索策略和相似度阈值 4)确认这是预期行为而非错误",
    "error_type": "hook_integration"
  },
  "hash_key": "707a7e8610c8b62a",
  "metadata": {
    "error_type": "hook_integration"
  },
  "created_at": "2026-02-03T11:41:21.293226",
  "last_used": "2026-02-03T11:41:21.293226",
  "usage_count": 0,
  "success_rate": 0.0,
  "priority": 2,
  "tags": [
    "hook_system",
    "memory_system",
    "integration",
    "normal_behavior",
    "troubleshooting",
    "error",
    "solution"
  ],
  "source": "user",
  "confidence": 1.0
}