{
  "id": "f7ade1f0-b8eb-4a92-a9b8-dd09a102dddf",
  "type": "best_practice",
  "content": {
    "title": "多系统集成验证策略",
    "description": "验证多个系统集成时的最佳实践：1)独立系统功能验证-确保每个系统单独工作正常 2)系统间通信测试-验证API调用和数据传递 3)数据一致性检查-确保跨系统数据同步 4)性能影响评估-测试集成对性能的影响 5)错误传播控制-确保错误不会级联传播",
    "category": "integration_testing"
  },
  "hash_key": "4e85d4cfedafaafe",
  "metadata": {
    "category": "integration_testing"
  },
  "created_at": "2026-02-03T11:41:21.296226",
  "last_used": "2026-02-03T11:41:21.296226",
  "usage_count": 0,
  "success_rate": 0.0,
  "priority": 2,
  "tags": [
    "integration",
    "testing",
    "multi_system",
    "verification",
    "architecture",
    "integration_testing",
    "best_practice"
  ],
  "source": "user",
  "confidence": 1.0
}