{
  "mcpServers": {
    "filesystem": {
      "command": "npx",
      "args": [
        "-y",
        "@modelcontextprotocol/server-filesystem",
        "."
      ],
      "env": {
        "FILESYSTEM_MAX_FILE_SIZE": "10MB",
        "FILESYSTEM_ALLOWED_EXTENSIONS": ".py,.js,.ts,.md,.json,.yaml,.yml,.txt"
      },
      "disabled": false,
      "autoApprove": [
        "read_text_file",
        "list_directory",
        "search_files",
        "get_file_info",
        "directory_tree"
      ]
    },
    "memory": {
      "command": "npx",
      "args": [
        "-y",
        "@modelcontextprotocol/server-memory"
      ],
      "env": {
        "MEMORY_MAX_ENTITIES": "10000",
        "MEMORY_PERSISTENCE": "true"
      },
      "disabled": false,
      "autoApprove": [
        "create_entities",
        "search_nodes",
        "read_graph",
        "open_nodes",
        "add_observations",
        "create_relations"
      ]
    }
  },
  "_metadata": {
    "version": "3.0",
    "description": "版本3.0统一MCP基础配置，所有平台共享",
    "last_updated": "2026-02-03T14:13:45.367172",
    "inheritance": "此配置为基础配置，平台特定配置将继承并覆盖差异部分"
  }
}